gprim/__init__.py
gprim/annotation.py
gprim/dataset.py
gprim/genome.py
gprim-0.23.dist-info/METADATA
gprim-0.23.dist-info/WHEEL
gprim-0.23.dist-info/top_level.txt
gprim-0.23.dist-info/RECORD
