Metadata-Version: 2.2
Name: gprim
Version: 0.23
Summary: Utility functions for working with statistical genetic data
Home-page: https://github.com/yakirr/gprim
Author: Yakir Reshef
Author-email: yreshef@broadinstitute.org
Classifier: Programming Language :: Python :: 3
Classifier: License :: OSI Approved :: MIT License
Classifier: Operating System :: OS Independent
Requires-Python: >=3
Requires-Dist: pysnptools
Requires-Dist: pybedtools
Requires-Dist: ypy
